nbuild/__init__.py
nbuild/build.py
nbuild/deliverable.py
nbuild/flowchart_gen.py
nbuild/http_test_server.py
nbuild/project.py
nbuild/test.py
nbuild/util.py
nbuild-0.0.1.dist-info/METADATA
nbuild-0.0.1.dist-info/WHEEL
nbuild-0.0.1.dist-info/top_level.txt
nbuild-0.0.1.dist-info/RECORD
