Metadata-Version: 2.1
Name: nbuild
Version: 0.0.1
Summary: A modern project-as-code specification, build, testing, and report generation library.
Home-page: https://github.com/Jeffrey-P-McAteer/nbuild
Author: Jeffrey McAteer
Author-email: jeffrey.p.mcateer@gmail.com
License: UNKNOWN
Platform: UNKNOWN
Classifier: Programming Language :: Python :: 3
Classifier: License :: OSI Approved :: MIT License
Classifier: Operating System :: OS Independent
Requires-Python: >=3.6
